{
    "Mapping" : {
        "xTiles" : 1,
        "yTiles" : 1,
        "zTiles" : 1,
        "sampleId" : -1,
        "wallTime" : 10
    },

    "Grid" : {
        "xNum" : 64,
        "yNum" : 64,
        "zNum" : 64,
        "origin" : [0.0, 0.0, 0.0],
        "xWidth" : 6.283185307179586,
        "yWidth" : 6.283185307179586,
        "zWidth" : 6.283185307179586
    },

    "BC" : {
        "xBCLeft"  : {
            "type" : "Periodic"
        },
        "xBCRight" : {
            "type" : "Periodic"
        },
        "yBCLeft"  : {
            "type" : "Periodic"
        },
        "yBCRight" : {
            "type" : "Periodic"
        },
        "zBCLeft"  : {
            "type" : "Periodic"
        },
        "zBCRight" : {
            "type" : "Periodic"
        }
    },

    "Integrator" : {
        "finalTime" : 20.00001,
        "maxIter" : 5,
        "cfl" : 1.0,
        "fixedDeltaTime" : -1.0
    },

    "Flow" : {
        "gasConstant" : 20.4128,
        "gamma" : 1.4,
        "prandtl" : 0.7,
        "viscosityModel" : {
            "type" : "PowerLaw",
            "viscRef" : 0.00044,
            "tempRef" : 1.0
        },
        "init" : {
            "type" : "TaylorGreen3DVortex",
            "density" : 1.0,
            "pressure" : 100.0,
            "velocity" : 2.0
        },
        "bodyForce" : [0.0, 0.0, 0.0],
        "turbForcing" : false
    },

    "Particles" : {
        "init" : {
            "type" : "Uniform",
            "num" : 1000,
            "density" : 8900.0,
            "temperature" : 250.0,
            "diameter" : 5e-3
        },
        "maxNum" : 1000,
        "restitutionCoeff" : 1.0,
        "convectiveCoeff" : 0.7,
        "absorptivity" : 1.0,
        "heatCapacity" : 0.7,
        "bodyForce" : [0.0, 0.0, 0.0],
        "maxSkew" : 1.5,
        "maxXferNum" : 100
    },

    "Radiation" : {
        "type" : "Algebraic",
        "intensity" : 1e3
    },

    "IO" : {
        "wrtRestart" : false,
        "restartEveryTimeSteps" : -1,
        "consoleFrequency" : 1,
        "headerFrequency" : 10,
        "probes" : []
    }
}
